mcp_multi_server/__init__.py
mcp_multi_server/client.py
mcp_multi_server/config.py
mcp_multi_server/types.py
mcp_multi_server/utils.py
mcp_multi_server-1.0.0.dist-info/METADATA
mcp_multi_server-1.0.0.dist-info/WHEEL
mcp_multi_server-1.0.0.dist-info/licenses/LICENSE
mcp_multi_server-1.0.0.dist-info/RECORD
