Metadata-Version: 2.4
Name: mcp-multi-server
Version: 1.0.0
Summary: A Python library for managing connections to multiple Model Context Protocol (MCP) servers
License-File: LICENSE
Keywords: mcp,model-context-protocol,multi-server,openai,llm,ai
Author: Antonio Pisani
Author-email: antonio.pisani@gmail.com
Requires-Python: >=3.10
Classifier: Development Status :: 4 - Beta
Classifier: Intended Audience :: Developers
Classifier: License :: OSI Approved :: MIT License
Classifier: Programming Language :: Python :: 3
Classifier: Programming Language :: Python :: 3.10
Classifier: Programming Language :: Python :: 3.11
Classifier: Programming Language :: Python :: 3.12
Classifier: Topic :: Software Development :: Libraries :: Python Modules
Classifier: Topic :: Scientific/Engineering :: Artificial Intelligence
Provides-Extra: examples
Provides-Extra: openai
Requires-Dist: mcp (>=1.13.1,<2.0.0)
Requires-Dist: openai (>=1.102.0,<2.0.0) ; extra == "examples"
Requires-Dist: openai (>=1.102.0,<2.0.0) ; extra == "openai"
Requires-Dist: pillow (>=10.0.0,<11.0.0) ; extra == "examples"
Requires-Dist: pyautogui (>=0.9.54,<0.10.0) ; extra == "examples"
Requires-Dist: pydantic (>=2.0.0,<3.0.0)
Requires-Dist: pyscreeze (>=1.0.1,<2.0.0) ; extra == "examples"
Requires-Dist: python-dotenv (>=1.1.0,<2.0.0) ; extra == "examples"
Project-URL: Documentation, https://mcp-multi-server.readthedocs.io/
Project-URL: Issue Tracker, https://github.com/apisani1/mcp-multi-server/issues
Project-URL: Release Notes, https://github.com/apisani1/mcp-multi-server/releases
Project-URL: Source Code, https://github.com/apisani1/mcp-multi-server
